target_ports/__init__.py
target_ports/target_ports.py
target_ports-2.1.dist-info/LICENSE
target_ports-2.1.dist-info/METADATA
target_ports-2.1.dist-info/WHEEL
target_ports-2.1.dist-info/entry_points.txt
target_ports-2.1.dist-info/top_level.txt
target_ports-2.1.dist-info/RECORD
