Metadata-Version: 2.1
Name: target-ports
Version: 2.1
Summary: Scan ports of a target
Author-email: Soumyo Deep Gupta <deep.main.ac@gmail.com>
Maintainer-email: Soumyo Deep Gupta <deep.main.ac@gmail.com>
License: License
Project-URL: GitHub, https://github.com/d33pster/target-ports
Project-URL: Issues, https://github.com/d33pster/target-ports/issues
Project-URL: Documentation, https://d33pster.github.io/target-ports/
Keywords: d33pster,port scanner,port,scanner,recon,portscanner,target-ports,targetports
Classifier: Development Status :: 4 - Beta
Classifier: Intended Audience :: Developers
Classifier: Topic :: Software Development
Classifier: Programming Language :: Python :: 3.10
Classifier: Programming Language :: Python :: 3.11
Classifier: Programming Language :: Python :: 3.12
Classifier: Operating System :: OS Independent
Requires-Python: >3.9
License-File: LICENSE
Requires-Dist: termcolor
Requires-Dist: optioner >=1.4.5
